{
  "commit_index": "15f90e0",
  "commit_url": "https://github.com/typeorm/typeorm/commit/15f90e0be897f5bd2f4dac1d1e8d24f539a842a8",
  "commit": {
    "commit_message": [
      "fix",
      "support",
      "async",
      "import",
      "datasource",
      "cli",
      "8914",
      "8917"
    ],
    "description": [
      "fix",
      "await",
      "datasource",
      "export",
      "file",
      "support",
      "async",
      "loading",
      "fix",
      "prettier",
      "error",
      "updated",
      "code",
      "style",
      "co-authored-by",
      "umed",
      "khudoiberdiev",
      "pleerock.me",
      "gmail.com"
    ],
    "changed_files_count": 1,
    "changed_files": [
      "src/commands/CommandUtils.ts"
    ],
    "changed_files_content": [],
    "parent": "bb33cd0f23d566c0d87fcb57e42bd611761cc106"
  },
  "pull_requests": [
    {
      "pr_title": [
        "fix",
        "8914",
        "8917"
      ],
      "total_discussions": 5,
      "discussions": [
        {
          "discussion_number": 1,
          "comments": [
            {
              "type": "pr_description",
              "content": [
                "description",
                "changesupport",
                "async",
                "import",
                "datasource",
                "cli.fixes",
                "8914pull-request",
                "checklistcode",
                "up-to-date",
                "themasterbranchnpm",
                "run",
                "formatto",
                "apply",
                "prettier",
                "formattingnpm",
                "run",
                "testpasses",
                "changethis",
                "pull",
                "request",
                "link",
                "relevant",
                "issue",
                "asfixes",
                "0000there",
                "new",
                "updated",
                "unit",
                "test",
                "validating",
                "changedocumentation",
                "updated",
                "reflect",
                "changethe",
                "new",
                "commits",
                "follow",
                "convention",
                "explained",
                "incontributing.md"
              ],
              "author": "pleerock"
            }
          ]
        },
        {
          "discussion_number": 2,
          "comments": [
            {
              "content": [
                "question",
                "commandutils.loaddatasource",
                "work",
                "test",
                "new",
                "bugfix",
                "first",
                "'m",
                "trying",
                "create",
                "test",
                "work",
                "current",
                "version",
                "first",
                "adapting",
                "work",
                "async",
                "version",
                "reason",
                "instancechecker",
                "statement",
                "always",
                "false",
                "error",
                "always",
                "thrown",
                "test",
                "ca",
                "n't",
                "seem",
                "understand",
                "right",
                "test",
                "involves",
                "simple",
                "file",
                "exporting",
                "datasource",
                "instance",
                "like",
                "'m",
                "testing",
                "like",
                "console.log",
                "datasourcefileexports",
                "get",
                "confirmation",
                "'s",
                "actually",
                "datasource",
                "instance",
                "instancechecker",
                "never",
                "return",
                "true",
                "value",
                "wrong",
                "ginden",
                "pleerock"
              ]
            }
          ]
        },
        {
          "discussion_number": 3,
          "comments": [
            {
              "content": [
                "viniciusssantosnot",
                "sure",
                "might",
                "need",
                "debug",
                "check",
                "data",
                "source",
                "symbol",
                "value"
              ]
            }
          ]
        },
        {
          "discussion_number": 4,
          "comments": [
            {
              "content": [
                "update",
                "pushing",
                "look",
                "like",
                "really",
                "close"
              ]
            }
          ]
        },
        {
          "discussion_number": 5,
          "comments": [
            {
              "content": [
                "release",
                "issue"
              ]
            }
          ]
        }
      ]
    }
  ],
  "issues": [
    {
      "title": [
        "cli",
        "support",
        "async",
        "datasource"
      ],
      "labels": [
        "bug"
      ],
      "comments": [
        {
          "author": "anton-pavlov-deel",
          "content": [
            "issue",
            "description",
            "starting",
            "0.3.0",
            "version",
            "cli",
            "requires",
            "specify",
            "file",
            "datasource",
            "instance",
            "instead",
            "ormconfig",
            "trying",
            "export",
            "async",
            "created",
            "datasource",
            "fails",
            "expected",
            "behavior",
            "command",
            "ran",
            "successfully",
            "actual",
            "behavior",
            "command",
            "failed",
            "error",
            "error",
            "given",
            "data",
            "source",
            "file",
            "must",
            "contain",
            "export",
            "datasource",
            "instance",
            "step",
            "reproduce",
            "datasource",
            "defined",
            "file",
            "const",
            "builddatasource",
            "async",
            "//",
            "provided",
            "config-like",
            "functionality",
            "example",
            "fail",
            "anyway",
            "async",
            "function",
            "const",
            "dbconfig",
            "await",
            "config",
            "get",
            "'database",
            "return",
            "new",
            "datasource",
            "type",
            "'mysql",
            "host",
            "dbconfig",
            "host",
            "port",
            "3306",
            "username",
            "dbconfig",
            "username",
            "password",
            "dbconfig",
            "password",
            "database",
            "dbconfig",
            "database",
            "logging",
            "true",
            "entity",
            "typeormentities",
            "migration",
            "'./src/components/database/migrations/",
            ".ts",
            "export",
            "default",
            "builddatasource",
            "work",
            "though",
            "const",
            "builddatasource",
            "return",
            "new",
            "datasource",
            "type",
            "'mysql",
            "host",
            "'127.0.0.1",
            "port",
            "3306",
            "username",
            "'test",
            "password",
            "'test",
            "database",
            "'test",
            "logging",
            "true",
            "entity",
            "typeormentities",
            "migration",
            "'./src/components/database/migrations/",
            ".ts",
            "export",
            "default",
            "builddatasource",
            "environment",
            "dependency",
            "version",
            "operating",
            "system",
            "ubuntu",
            "20.04.4",
            "lts",
            "node.js",
            "version",
            "v16.13.0",
            "typescript",
            "version",
            "4.6.3",
            "typeorm",
            "version",
            "0.3.4",
            "relevant",
            "database",
            "driver",
            "tested",
            "mysql",
            "think",
            "driver",
            "problem",
            "db",
            "type",
            "reproducible",
            "aurora-mysql",
            "aurora-postgres",
            "better-sqlite3",
            "cockroachdb",
            "cordova",
            "expo",
            "mongodb",
            "mysql",
            "yes",
            "nativescript",
            "oracle",
            "postgres",
            "react-native",
            "sap",
            "spanner",
            "sqlite",
            "sqlite-abstract",
            "sqljs",
            "sqlserver",
            "willing",
            "resolve",
            "issue",
            "submitting",
            "pull",
            "request",
            "\u2716\ufe0f",
            "yes",
            "time",
            "know",
            "start",
            "\u2716\ufe0f",
            "yes",
            "time",
            "n't",
            "know",
            "start",
            "would",
            "need",
            "guidance",
            "\u2716\ufe0f",
            "\u2019",
            "time",
            "support",
            "using",
            "donation",
            "development",
            "\u2019",
            "time",
            "\u2019",
            "okay",
            "wait",
            "community",
            "maintainer",
            "resolve",
            "issue"
          ]
        },
        {
          "author": "Ginden",
          "content": [
            "using",
            "esm",
            "module",
            "try",
            "export",
            "default",
            "await"
          ]
        },
        {
          "author": "Ginden",
          "content": [
            "yes",
            "make",
            "sense",
            "though",
            "n't",
            "need",
            "make",
            "instanceof",
            "promise",
            "check",
            "need",
            "replace",
            "line",
            "t",
            "const",
            "datasourceexports",
            "let",
            "fileexport",
            "datasourcefileexports",
            "instancechecker.isdatasource",
            "datasourcefileexports",
            "fileexport",
            "datasourceexports.push",
            "datasourcefileexports",
            "fileexport",
            "t",
            "const",
            "datasourceexports",
            "let",
            "fileexport",
            "datasourcefileexports",
            "const",
            "fileexportvalue",
            "await",
            "datasourcefileexports",
            "fileexport",
            "instancechecker.isdatasource",
            "fileexportvalue",
            "datasourceexports.push",
            "fileexportvalue",
            "please",
            "feel",
            "free",
            "open",
            "pr",
            "pavlovanton"
          ]
        },
        {
          "author": "SimonCockx",
          "content": [
            "quick",
            "dirty",
            "hack",
            "used",
            "get",
            "resolved",
            "t",
            "import",
            "datasource",
            "datasourceoptions",
            "instancechecker",
            "'typeorm",
            "import",
            "dotenv",
            "'dotenv",
            "dotenv.config",
            "function",
            "patchasyncdatasourcesetup",
            "const",
            "oldisdatasource",
            "instancechecker.isdatasource",
            "instancechecker.isdatasource",
            "function",
            "obj",
            "unknown",
            "obj",
            "datasource",
            "obj",
            "instanceof",
            "promise",
            "return",
            "true",
            "return",
            "oldisdatasource",
            "obj",
            "patchasyncdatasourcesetup",
            "const",
            "builddatasource",
            "async",
            "...",
            "export",
            "default",
            "builddatasource"
          ]
        },
        {
          "author": "DanielMaranhao",
          "content": [
            "news",
            "async",
            "datasource"
          ]
        }
      ]
    }
  ],
  "security": null
}