{
  "commit_index": "7177e3a",
  "commit_url": "https://github.com/n8n-io/n8n/commit/7177e3aab082cc7964698221a9440cd92dfaed03",
  "commit": {
    "commit_message": [
      "fix",
      "core",
      "register",
      "transition",
      "handler",
      "module",
      "init"
    ],
    "description": [],
    "changed_files_count": 3,
    "changed_files": [
      "packages/cli/src/commands/base-command.ts",
      "packages/cli/src/commands/start.ts",
      "packages/cli/src/modules/insights/insights.service.ts"
    ],
    "changed_files_content": [],
    "parent": "cb81826cf16a215e1da08432e5bb6ce29db1099e"
  },
  "pull_requests": [
    {
      "pr_title": [
        "fix",
        "core",
        "register",
        "transition",
        "handler",
        "module",
        "init"
      ],
      "total_discussions": 5,
      "discussions": [
        {
          "discussion_number": 1,
          "comments": [
            {
              "type": "pr_description",
              "content": [
                "moved",
                "module",
                "loading",
                "entrypoint",
                "allow",
                "module",
                "register",
                "db",
                "entity",
                "establish",
                "db",
                "connection",
                "missed",
                "early",
                "stage",
                "license",
                "initialized",
                "yet",
                "evaluates",
                "tofalseand",
                "fail",
                "register",
                "leadership",
                "transition",
                "handlers.this",
                "pr",
                "move",
                "transition",
                "handler",
                "registration",
                "back",
                "itsoriginal",
                "positionafter",
                "module",
                "initialize",
                "also",
                "removed",
                "excess",
                "decorator",
                "left",
                "behind",
                "misresolved",
                "merge.to",
                "test",
                "start",
                "two",
                "main",
                "wind",
                "leader",
                "watch",
                "new",
                "leader",
                "start",
                "decorated",
                "service",
                "adding",
                "trigger",
                "pollers",
                "wait",
                "tracking",
                "execution",
                "pruning"
              ],
              "author": "ivov"
            }
          ]
        }
      ]
    }
  ],
  "issues": null,
  "security": null
}